<?xml version="1.0" encoding="utf-8" ?><dwsync><file name=".gitignore" server="somewhereupthere.com/somewhereupthere.com/test/unee-t/" local="3618886806" remote="3618887285" Dst="-1" /><file name=".travis.yml" server="somewhereupthere.com/somewhereupthere.com/test/unee-t/" local="3618886806" remote="3618887287" Dst="-1" /><file name="LICENSE" server="somewhereupthere.com/somewhereupthere.com/test/unee-t/" local="3618886806" remote="3618887289" Dst="-1" /><file name="main.go" server="somewhereupthere.com/somewhereupthere.com/test/unee-t/" local="3618886806" remote="3618887290" Dst="-1" /><file name="main_test.go" server="somewhereupthere.com/somewhereupthere.com/test/unee-t/" local="3618886806" remote="3618887291" Dst="-1" /><file name="Makefile" server="somewhereupthere.com/somewhereupthere.com/test/unee-t/" local="3618886806" remote="3618887292" Dst="-1" /><file name="structs.go" server="somewhereupthere.com/somewhereupthere.com/test/unee-t/" local="3618886806" remote="3618887293" Dst="-1" /><file name="up.json.in" server="somewhereupthere.com/somewhereupthere.com/test/unee-t/" local="3618886806" remote="3618887328" Dst="-1" /></dwsync>